{
  "project_info": {
    "project_number": "525398884433",
    "project_id": "exam-baba-ux7hq8",
    "storage_bucket": "exam-baba-ux7hq8.appspot.com"
  },
  "client": [
    {
      "client_info": {
        "mobilesdk_app_id": "1:525398884433:android:a4e6d704d35d3440fa7870",
        "android_client_info": {
          "package_name": "com.ruffbook.aarogyam"
        }
      },
      "oauth_client": [
        {
          "client_id": "525398884433-hhj3m2qqab3l32h4a7nl3shtvjk2134d.apps.googleusercontent.com",
          "client_type": 1,
          "android_info": {
            "package_name": "com.ruffbook.aarogyam",
            "certificate_hash": "9bbb3186b2189ef16d8f272bdab59362c395cbb4"
          }
        },
        {
          "client_id": "525398884433-og352d7s2vio5c8j81flsjo9j189bph0.apps.googleusercontent.com",
          "client_type": 3
        }
      ],
      "api_key": [
        {
          "current_key": "AIzaSyB9_o-6nH0qAxAq62t5xdMQ25K_lkmAAEA"
        }
      ],
      "services": {
        "appinvite_service": {
          "other_platform_oauth_client": [
            {
              "client_id": "525398884433-og352d7s2vio5c8j81flsjo9j189bph0.apps.googleusercontent.com",
              "client_type": 3
            },
            {
              "client_id": "525398884433-60imb9j6e8k242lenltb00l33mrgb0o7.apps.googleusercontent.com",
              "client_type": 2,
              "ios_info": {
                "bundle_id": "com.ruffbook.healthliteracy"
              }
            }
          ]
        }
      }
    },
    {
      "client_info": {
        "mobilesdk_app_id": "1:525398884433:android:a0f7c1486c920125fa7870",
        "android_client_info": {
          "package_name": "com.ruffbook.classmate"
        }
      },
      "oauth_client": [
        {
          "client_id": "525398884433-0efig25a1chri9f73g9jcgqhb4qdlt4i.apps.googleusercontent.com",
          "client_type": 1,
          "android_info": {
            "package_name": "com.ruffbook.classmate",
            "certificate_hash": "9bbb3186b2189ef16d8f272bdab59362c395cbb4"
          }
        },
        {
          "client_id": "525398884433-nhoj8vm6r76dkmm2a7j8kdnrt3gcbteq.apps.googleusercontent.com",
          "client_type": 1,
          "android_info": {
            "package_name": "com.ruffbook.classmate",
            "certificate_hash": "d32f53fc46b87e3af8108e4250af8e8594685322"
          }
        },
        {
          "client_id": "525398884433-og352d7s2vio5c8j81flsjo9j189bph0.apps.googleusercontent.com",
          "client_type": 3
        }
      ],
      "api_key": [
        {
          "current_key": "AIzaSyB9_o-6nH0qAxAq62t5xdMQ25K_lkmAAEA"
        }
      ],
      "services": {
        "appinvite_service": {
          "other_platform_oauth_client": [
            {
              "client_id": "525398884433-og352d7s2vio5c8j81flsjo9j189bph0.apps.googleusercontent.com",
              "client_type": 3
            },
            {
              "client_id": "525398884433-60imb9j6e8k242lenltb00l33mrgb0o7.apps.googleusercontent.com",
              "client_type": 2,
              "ios_info": {
                "bundle_id": "com.ruffbook.healthliteracy"
              }
            }
          ]
        }
      }
    },
    {
      "client_info": {
        "mobilesdk_app_id": "1:525398884433:android:91851c2b0539a043fa7870",
        "android_client_info": {
          "package_name": "com.ruffbook.healthliteracy"
        }
      },
      "oauth_client": [
        {
          "client_id": "525398884433-9vo56gehc2k307eaqh71h2c0ahs7c339.apps.googleusercontent.com",
          "client_type": 1,
          "android_info": {
            "package_name": "com.ruffbook.healthliteracy",
            "certificate_hash": "9bbb3186b2189ef16d8f272bdab59362c395cbb4"
          }
        },
        {
          "client_id": "525398884433-og352d7s2vio5c8j81flsjo9j189bph0.apps.googleusercontent.com",
          "client_type": 3
        }
      ],
      "api_key": [
        {
          "current_key": "AIzaSyB9_o-6nH0qAxAq62t5xdMQ25K_lkmAAEA"
        }
      ],
      "services": {
        "appinvite_service": {
          "other_platform_oauth_client": [
            {
              "client_id": "525398884433-og352d7s2vio5c8j81flsjo9j189bph0.apps.googleusercontent.com",
              "client_type": 3
            },
            {
              "client_id": "525398884433-60imb9j6e8k242lenltb00l33mrgb0o7.apps.googleusercontent.com",
              "client_type": 2,
              "ios_info": {
                "bundle_id": "com.ruffbook.healthliteracy"
              }
            }
          ]
        }
      }
    }
  ],
  "configuration_version": "1"
}